edwh_nostr_messagebus/__about__.py
edwh_nostr_messagebus/__init__.py
edwh_nostr_messagebus/client.py
edwh_nostr_messagebus-0.4.1.dist-info/METADATA
edwh_nostr_messagebus-0.4.1.dist-info/WHEEL
edwh_nostr_messagebus-0.4.1.dist-info/licenses/LICENSE.txt
edwh_nostr_messagebus-0.4.1.dist-info/RECORD
