Metadata-Version: 2.1
Name: edwh_nostr_messagebus
Version: 0.4.1
Summary: EducationWarehouse NOSTR Messagebus
Project-URL: Documentation, https://github.com/educationwarehouse/edwh_nostr_messagebus#readme
Project-URL: Issues, https://github.com/educationwarehouse/edwh_nostr_messagebus/issues
Project-URL: Source, https://github.com/educationwarehouse/edwh_nostr_messagebus
Author-email: Remco <remco@educationwarehouse.nl>
License-Expression: MIT
License-File: LICENSE.txt
Keywords: education,edwh,nostr
Classifier: Development Status :: 4 - Beta
Classifier: Programming Language :: Python
Classifier: Programming Language :: Python :: 3.11
Classifier: Programming Language :: Python :: 3.12
Classifier: Programming Language :: Python :: Implementation :: CPython
Requires-Python: >=3.11
Requires-Dist: edwh
Requires-Dist: monstr
Requires-Dist: pyinvoke
